mono_connect/__init__.py
mono_connect/client.py
mono_customer/__init__.py
mono_customer/client.py
mono_directpay/__init__.py
mono_directpay/client.py
mono_lookup/__init__.py
mono_lookup/client.py
mono_sdk-0.1.4.dist-info/METADATA
mono_sdk-0.1.4.dist-info/WHEEL
mono_sdk-0.1.4.dist-info/top_level.txt
mono_sdk-0.1.4.dist-info/RECORD
