Metadata-Version: 2.4
Name: mono-sdk
Version: 0.1.4
Summary: Python SDK for Mono APIs (Connect, Customer, Directpay, Lookup)
Home-page: https://github.com/ezeisraeljohn/mono-sdk
Author: Eze Israel John
Author-email: ezeisraeljohn@gmail.com
License: MIT
Project-URL: Source, https://github.com/ezeisraeljohn/mono-sdk
Project-URL: Documentation, https://github.com/ezeisraeljohn/mono-sdk#readme
Classifier: Programming Language :: Python :: 3
Classifier: Operating System :: OS Independent
Classifier: License :: OSI Approved :: MIT License
Classifier: Development Status :: 3 - Alpha
Classifier: Intended Audience :: Developers
Classifier: Topic :: Software Development :: Libraries :: Python Modules
Requires-Python: >=3.6
Requires-Dist: requests>=2.20.0
Dynamic: author
Dynamic: author-email
Dynamic: classifier
Dynamic: description
Dynamic: description-content-type
Dynamic: home-page
Dynamic: license
Dynamic: project-url
Dynamic: requires-dist
Dynamic: requires-python
Dynamic: summary
